twat/__init__.py
twat/__version__.py
twat-2.7.5.dist-info/METADATA
twat-2.7.5.dist-info/WHEEL
twat-2.7.5.dist-info/entry_points.txt
twat-2.7.5.dist-info/licenses/LICENSE
twat-2.7.5.dist-info/RECORD
