Metadata-Version: 2.4
Name: twat
Version: 2.7.5
Project-URL: Documentation, https://github.com/twardoch/twat#readme
Project-URL: Issues, https://github.com/twardoch/twat/issues
Project-URL: Source, https://github.com/twardoch/twat
Author-email: Adam Twardoch <adam+github@twardoch.com>
License-Expression: MIT
License-File: LICENSE
Classifier: Development Status :: 4 - Beta
Classifier: Programming Language :: Python
Classifier: Programming Language :: Python :: 3.10
Classifier: Programming Language :: Python :: 3.11
Classifier: Programming Language :: Python :: 3.12
Classifier: Programming Language :: Python :: Implementation :: CPython
Classifier: Programming Language :: Python :: Implementation :: PyPy
Requires-Python: >=3.10
Requires-Dist: fire>=0.7.0
Requires-Dist: importlib-metadata>=8.6.1
Requires-Dist: importlib-resources>=6.5.2
Requires-Dist: loguru>=0.7.3
Requires-Dist: pydantic>=2.10.6
Requires-Dist: python-dotenv>=1.0.1
Requires-Dist: rich>=13.9.4
Requires-Dist: tomli>=2.2.1
Requires-Dist: typing-extensions>=4.0.0; python_version < '3.10'
Provides-Extra: all
Requires-Dist: fire>=0.7.0; extra == 'all'
Requires-Dist: importlib-metadata>=8.6.1; extra == 'all'
Requires-Dist: importlib-resources>=6.5.2; extra == 'all'
Requires-Dist: loguru>=0.7.3; extra == 'all'
Requires-Dist: pydantic>=2.10.6; extra == 'all'
Requires-Dist: python-dotenv>=1.0.1; extra == 'all'
Requires-Dist: rich>=13.9.4; extra == 'all'
Requires-Dist: tomli>=2.2.1; extra == 'all'
Requires-Dist: twat-audio[all]>=2.1.3; extra == 'all'
Requires-Dist: twat-cache[all]>=2.6.7; extra == 'all'
Requires-Dist: twat-ez[all]>=2.6.2; extra == 'all'
Requires-Dist: twat-fs[all]>=2.6.2; extra == 'all'
Requires-Dist: twat-genai[all]>=2.6.2; extra == 'all'
Requires-Dist: twat-hatch[all]>=2.6.2; extra == 'all'
Requires-Dist: twat-image[all]>=2.6.2; extra == 'all'
Requires-Dist: twat-labs[all]>=2.6.2; extra == 'all'
Requires-Dist: twat-llm[all]>=2.6.2; extra == 'all'
Requires-Dist: twat-mp[all]>=2.6.2; extra == 'all'
Requires-Dist: twat-search[all]>=2.6.2; extra == 'all'
Requires-Dist: twat-speech[all]>=2.6.2; extra == 'all'
Requires-Dist: twat-task[all]>=2.6.2; extra == 'all'
Requires-Dist: twat-text[all]>=2.6.2; extra == 'all'
Requires-Dist: twat-video[all]>=2.6.2; extra == 'all'
Requires-Dist: typing-extensions>=4.0.0; (python_version < '3.10') and extra == 'all'
Provides-Extra: audio
Requires-Dist: twat-audio[all]>=0.0.1; extra == 'audio'
Provides-Extra: cache
Requires-Dist: twat-cache[all]>=2.6.7; extra == 'cache'
Provides-Extra: coding
Requires-Dist: twat-coding[all]>=0.0.1; extra == 'coding'
Provides-Extra: dev
Requires-Dist: mypy>=1.0.0; extra == 'dev'
Requires-Dist: pre-commit>=4.0.0; extra == 'dev'
Requires-Dist: ruff>=0.1.0; extra == 'dev'
Provides-Extra: ez
Requires-Dist: twat-ez[all]>=2.6.2; extra == 'ez'
Provides-Extra: fs
Requires-Dist: twat-fs[all]>=2.6.2; extra == 'fs'
Provides-Extra: genai
Requires-Dist: twat-genai[all]>=2.6.2; extra == 'genai'
Provides-Extra: hatch
Requires-Dist: twat-hatch[all]>=2.6.2; extra == 'hatch'
Provides-Extra: image
Requires-Dist: twat-image[all]>=2.6.2; extra == 'image'
Provides-Extra: labs
Requires-Dist: twat-labs[all]>=1.7.5; extra == 'labs'
Provides-Extra: llm
Requires-Dist: twat-llm[all]>=2.6.2; extra == 'llm'
Provides-Extra: mp
Requires-Dist: twat-mp[all]>=2.6.2; extra == 'mp'
Provides-Extra: os
Requires-Dist: twat-os[all]>=2.6.2; extra == 'os'
Provides-Extra: search
Requires-Dist: twat-search[all]>=2.6.2; extra == 'search'
Provides-Extra: speech
Requires-Dist: twat-speech[all]>=2.6.2; extra == 'speech'
Provides-Extra: task
Requires-Dist: twat-task[all]>=2.6.2; extra == 'task'
Provides-Extra: test
Requires-Dist: pytest-benchmark[histogram]>=5.1.0; extra == 'test'
Requires-Dist: pytest-cov>=6.0.0; extra == 'test'
Requires-Dist: pytest-xdist>=3.6.1; extra == 'test'
Requires-Dist: pytest>=8.3.4; extra == 'test'
Provides-Extra: text
Requires-Dist: twat-text[all]>=2.6.2; extra == 'text'
Provides-Extra: video
Requires-Dist: twat-video[all]>=2.6.2; extra == 'video'
